sphinx_sitemap/__init__.py
sphinx_sitemap_lextudio-2.5.2.dist-info/LICENSE
sphinx_sitemap_lextudio-2.5.2.dist-info/METADATA
sphinx_sitemap_lextudio-2.5.2.dist-info/WHEEL
sphinx_sitemap_lextudio-2.5.2.dist-info/top_level.txt
sphinx_sitemap_lextudio-2.5.2.dist-info/RECORD
